pythran_openblas/__init__.py
pythran_openblas/placeholder.cpython-37m-x86_64-linux-gnu.so
pythran_openblas/include/openblas/cblas.h
pythran_openblas/include/openblas/openblas_config.h
pythran_openblas/lib64/libopenblas.a
pythran_openblas/lib64/pkgconfig/openblas.pc
pythran_openblas/share/cmake/OpenBLAS/OpenBLASConfig.cmake
pythran_openblas/share/cmake/OpenBLAS/OpenBLASConfigVersion.cmake
pythran_openblas/share/cmake/OpenBLAS/OpenBLASTargets-release.cmake
pythran_openblas/share/cmake/OpenBLAS/OpenBLASTargets.cmake
pythran_openblas-0.3.6.dist-info/LICENSE
pythran_openblas-0.3.6.dist-info/METADATA
pythran_openblas-0.3.6.dist-info/WHEEL
pythran_openblas-0.3.6.dist-info/top_level.txt
pythran_openblas-0.3.6.dist-info/RECORD
