Metadata-Version: 2.1
Name: pythran-openblas
Version: 0.3.6
Summary: Python packaging of OpenBLAS
Home-page: https://github.com/serge-sans-paille/pythran-openblas
Author: serge-sans-paille
Author-email: serge.guelton@telecom-bretagne.eu
License: BSD 3-Clause
Platform: UNKNOWN
